synchronous_ram.v
`timescale 1ns / 1ps

module synchronous_ram #(
    parameter DATA_WIDTH = 8,
    parameter ADDR_WIDTH = 4
)(
    input clk,
    input we,             // Write Enable
    input re,             // Read Enable
    input [ADDR_WIDTH-1:0] addr,
    input [DATA_WIDTH-1:0] din,
    output reg [DATA_WIDTH-1:0] dout
);

    // RAM memory
    reg [DATA_WIDTH-1:0] mem [(2**ADDR_WIDTH)-1:0];

    always @(posedge clk) begin
        if (we)
            mem[addr] <= din;          // Write operation
        if (re)
            dout <= mem[addr];         // Read operation
    end

endmodule

synchronous_ram_tb.v
`timescale 1ns / 1ps

module synchronous_ram_tb;

    parameter DATA_WIDTH = 8;
    parameter ADDR_WIDTH = 4;

    reg clk;
    reg we, re;
    reg [ADDR_WIDTH-1:0] addr;
    reg [DATA_WIDTH-1:0] din;
    wire [DATA_WIDTH-1:0] dout;

    // Instantiate the RAM
    synchronous_ram #(DATA_WIDTH, ADDR_WIDTH) uut (
        .clk(clk),
        .we(we),
        .re(re),
        .addr(addr),
        .din(din),
        .dout(dout)
    );

    // Clock generation
    initial begin
        clk = 0;
        forever #5 clk = ~clk; // 10ns clock period
    end

    // Test sequence
    initial begin
        $dumpfile("synchronous_ram.vcd");
        $dumpvars(0, synchronous_ram_tb);

        we = 0; re = 0; addr = 0; din = 0;

        // Write values
        #10;
        we = 1; re = 0;
        addr = 4'h3; din = 8'hAA; #10;
        addr = 4'h4; din = 8'hBB; #10;
        addr = 4'h5; din = 8'hCC; #10;

        // Read values
        we = 0; re = 1;
        addr = 4'h3; #10;
        addr = 4'h4; #10;
        addr = 4'h5; #10;

        // End simulation
        $display("Simulation complete");
        $finish;
    end

endmodule

synchronous_ram.vcd
$date
	Mon Jul 28 16:20:18 2025
$end
$version
	Icarus Verilog
$end
$timescale
	1ps
$end
$scope module synchronous_ram_tb $end
$var wire 8 ! dout [7:0] $end
$var reg 4 " addr [3:0] $end
$var reg 1 # clk $end
$var reg 8 $ din [7:0] $end
$var reg 1 % re $end
$var reg 1 & we $end
$scope module uut $end
$var wire 4 ' addr [3:0] $end
$var wire 1 ( clk $end
$var wire 8 ) din [7:0] $end
$var wire 1 * re $end
$var wire 1 + we $end
$var reg 8 , dout [7:0] $end
$upscope $end
$upscope $end
$enddefinitions $end
#0
$dumpvars
bx ,
0+
0*
b0 )
0(
b0 '
0&
0%
b0 $
0#
b0 "
bx !
$end
#5000
1#
1(
#10000
0#
0(
b10101010 $
b10101010 )
b11 "
b11 '
1&
1+
#15000
1#
1(
#20000
0#
0(
b10111011 $
b10111011 )
b100 "
b100 '
#25000
1#
1(
#30000
0#
0(
b11001100 $
b11001100 )
b101 "
b101 '
#35000
1#
1(
#40000
0#
0(
b11 "
b11 '
1%
1*
0&
0+
#45000
b10101010 ,
b10101010 !
1#
1(
#50000
0#
0(
b100 "
b100 '
#55000
b10111011 ,
b10111011 !
1#
1(
#60000
0#
0(
b101 "
b101 '
#65000
b11001100 ,
b11001100 !
1#
1(
